PyREMOT/__init__.py
PyREMOT/rmt.py
PyREMOT/saveRes.py
PyREMOT/test.py
PyREMOT/test4.py
PyREMOT/testFiEl.py
PyREMOT/testMesh.py
PyREMOT/test_component.py
PyREMOT/test_diffusivity.py
PyREMOT/test_heatCapacity.py
PyREMOT/test_pyremot.py
PyREMOT/test_rmt1.py
PyREMOT/test_rmt_C2.py
PyREMOT/test_rmt_C6.py
PyREMOT/test_rmt_CH4_6.py
PyREMOT/test_rmt_DME.py
PyREMOT/test_rmt_DME2.py
PyREMOT/test_rmt_DME3.py
PyREMOT/test_rmt_DME4.py
PyREMOT/test_rmt_DME5.py
PyREMOT/test_rmt_DME6.py
PyREMOT/test_rmt_N1_DME.py
PyREMOT/test_rmt_N2_CH4.py
PyREMOT/test_viscosity.py
PyREMOT/core/__init__.py
PyREMOT/core/config.py
PyREMOT/core/constants.py
PyREMOT/core/eqConstants.py
PyREMOT/core/errors.py
PyREMOT/core/setting.py
PyREMOT/core/store.py
PyREMOT/core/utilities.py
PyREMOT/data/__init__.py
PyREMOT/data/componentData.py
PyREMOT/data/dataGasViscosity.py
PyREMOT/data/initData.py
PyREMOT/data/inputDataGeneral.py
PyREMOT/data/inputDataReactor.py
PyREMOT/docs/__init__.py
PyREMOT/docs/batchReactor.py
PyREMOT/docs/bcSetting.py
PyREMOT/docs/cReactor.py
PyREMOT/docs/fluidFilm.py
PyREMOT/docs/gasTransPor.py
PyREMOT/docs/initialCal.py
PyREMOT/docs/modelSetting.py
PyREMOT/docs/pbHeterReactor.py
PyREMOT/docs/pbHomoReactor.py
PyREMOT/docs/pbReactor.py
PyREMOT/docs/pbReactor2.py
PyREMOT/docs/pfReactor.py
PyREMOT/docs/rmtCore.py
PyREMOT/docs/rmtReaction.py
PyREMOT/docs/rmtThermo.py
PyREMOT/docs/rmtUtility.py
PyREMOT/examples/__init__.py
PyREMOT/examples/data1.py
PyREMOT/examples/exp1.py
PyREMOT/examples/homoModels.py
PyREMOT/examples/particleModels.py
PyREMOT/examples/reactionList.py
PyREMOT/library/__init__.py
PyREMOT/library/plot.py
PyREMOT/library/saveResult.py
PyREMOT/solvers/__init__.py
PyREMOT/solvers/exp1.py
PyREMOT/solvers/exp2.py
PyREMOT/solvers/ocConfig.py
PyREMOT/solvers/odeSolver.py
PyREMOT/solvers/solCatParticle.py
PyREMOT/solvers/solCatParticle2.py
PyREMOT/solvers/solCatParticle3.py
PyREMOT/solvers/solCore.py
PyREMOT/solvers/solFiDi.py
PyREMOT/solvers/solFiEl.py
PyREMOT/solvers/solOrCo.py
PyREMOT-1.0.17.dist-info/LICENSE.md
PyREMOT-1.0.17.dist-info/METADATA
PyREMOT-1.0.17.dist-info/WHEEL
PyREMOT-1.0.17.dist-info/top_level.txt
PyREMOT-1.0.17.dist-info/RECORD
