Metadata-Version: 2.1
Name: PyREMOT
Version: 1.0.17
Summary: Python Reactor Modeling Tools (PyREMOT)
Home-page: https://pyremot.herokuapp.com/
Author: Sina Gilassi
Author-email: <sina.gilassi@gmail.com>
License: MIT
Keywords: python,chemical engineering,packed-bed reactor modeling,homogenous reactor,reaction engineering
Platform: UNKNOWN
Classifier: Development Status :: 1 - Planning
Classifier: Intended Audience :: Education
Classifier: Programming Language :: Python :: 3
Classifier: Operating System :: Unix
Classifier: Operating System :: MacOS :: MacOS X
Classifier: Operating System :: Microsoft :: Windows
License-File: LICENSE.md
